ducer/__init__.py
ducer/_fst.cp314-win_amd64.pyd
ducer/_fst.pyi
ducer/_version.py
ducer-1.2.0.dist-info/licenses/LICENSE
ducer-1.2.0.dist-info/METADATA
ducer-1.2.0.dist-info/WHEEL
ducer-1.2.0.dist-info/top_level.txt
ducer-1.2.0.dist-info/RECORD
