Metadata-Version: 2.4
Name: ducer
Version: 1.2.0
Summary: Fast and compact maps and sets with Billions of keys, based on finite-state-transducers.
Author-email: Joachim Folz <joachim.folz@dfki.de>
License-Expression: MIT
Project-URL: Homepage, https://github.com/jfolz/ducer
Project-URL: Documentation, https://ducer.readthedocs.io/stable/
Project-URL: Repository, https://github.com/jfolz/ducer
Project-URL: Issues, https://github.com/jfolz/ducer/issues
Project-URL: Changelog, https://github.com/jfolz/ducer/blob/main/CHANGELOG.md
Keywords: big data,compression,dataset,dict,finite-state-machines,finite-state-transducers,frozen,fst,map,serialization,set,streaming
Classifier: Development Status :: 5 - Production/Stable
Classifier: Intended Audience :: Developers
Classifier: Intended Audience :: Science/Research
Classifier: Intended Audience :: Information Technology
Classifier: Programming Language :: Rust
Classifier: Programming Language :: Python :: Implementation :: CPython
Classifier: Programming Language :: Python :: 3.9
Classifier: Programming Language :: Python :: 3.10
Classifier: Programming Language :: Python :: 3.11
Classifier: Programming Language :: Python :: 3.12
Classifier: Programming Language :: Python :: 3.13
Requires-Python: >=3.9
License-File: LICENSE
Dynamic: license-file
